tec/__init__.py
tec/ic/__init__.py
tec/ic/ia/__init__.py
tec/ic/ia/p2/__init__.py
tec/ic/ia/p2/g07/Controller.py
tec/ic/ia/p2/g07/Queries.py
tec/ic/ia/p2/g07/Relation.py
tec/ic/ia/p2/g07/__init__.py
tec/ic/ia/p2/g07/main.py
tec/ic/ia/p2/g07/tests/__init__.py
tec/ic/ia/p2/g07/tests/test_queries.py
tec.ic.ia.p2.g07.main-1.0.0.dist-info/METADATA
tec.ic.ia.p2.g07.main-1.0.0.dist-info/RECORD
tec.ic.ia.p2.g07.main-1.0.0.dist-info/WHEEL
tec.ic.ia.p2.g07.main-1.0.0.dist-info/top_level.txt
