Metadata-Version: 2.1
Name: tec.ic.ia.p2.g07.main
Version: 1.0.0
Summary: This repository contains the second project of Artificial Intelligence course from Instituto Tecnológico de Costa Rica, imparted by the professor Juan Manuel Esquivel. The project consists on some queries to search relations on a word database named "Etymological Wordnet" based by en.wiktionary.org.
Home-page: https://github.com/mamemo/Etimology-Relationships
Author: Trifuerza
Author-email: UNKNOWN
License: UNKNOWN
Platform: UNKNOWN
